openedx_hooks/__init__.py
openedx_hooks/signals/__init__.py
openedx_hooks/signals/auth/__init__.py
openedx_hooks/signals/auth/v1/__init__.py
openedx_hooks/signals/enrollment/__init__.py
openedx_hooks/signals/enrollment/v1/__init__.py
openedx_hooks-0.1.0.dist-info/LICENSE.txt
openedx_hooks-0.1.0.dist-info/METADATA
openedx_hooks-0.1.0.dist-info/WHEEL
openedx_hooks-0.1.0.dist-info/top_level.txt
openedx_hooks-0.1.0.dist-info/RECORD
