Metadata-Version: 2.1
Name: openedx-hooks
Version: 0.1.0
Summary: Open edX hooks definitions and utilities.
Home-page: https://github.com/edx/openedx-hooks
Author: edX
Author-email: oscm@edx.org
License: AGPL 3.0
Keywords: Python edx
Platform: UNKNOWN
Classifier: Development Status :: 3 - Alpha
Classifier: Intended Audience :: Developers
Classifier: License :: OSI Approved :: GNU Affero General Public License v3 or later (AGPLv3+)
Classifier: Natural Language :: English
Classifier: Programming Language :: Python :: 3
Classifier: Programming Language :: Python :: 3.8
Requires-Python: >=3.8
Requires-Dist: django
